ned/__init__.py
ned/actors/__init__.py
ned/actors/__main__.py
ned/actors/candidate_generation.py
ned/actors/candidate_ranking.py
ned/actors/dataset/__init__.py
ned/actors/dataset/auto_dataset.py
ned/actors/dataset/dataset.py
ned/actors/dataset/prelude.py
ned/actors/dataset/utils.py
ned/actors/db.py
ned/actors/entity_recognition.py
ned/actors/evaluate_helper.py
ned/autodata/__init__.py
ned/autodata/erv1.py
ned/autodata/fbhct.py
ned/autodata/fbt.py
ned/autodata/fcom.py
ned/autodata/freg.py
ned/autodata/fv1.py
ned/autodata/lv1.py
ned/autodata/mv1.py
ned/autodata/prelude.py
ned/autodata/utils.py
ned/candidate_generation/__init__.py
ned/candidate_generation/common.py
ned/candidate_generation/localsearch.py
ned/candidate_generation/mtab_wrapper.py
ned/candidate_generation/oracle_semtyper.py
ned/candidate_generation/pyserini/__init__.py
ned/candidate_generation/pyserini/analyzer.py
ned/candidate_generation/pyserini/configuration.py
ned/candidate_generation/pyserini/document.py
ned/candidate_generation/pyserini/indexing.py
ned/candidate_generation/pyserini/search.py
ned/candidate_generation/pyserini_wrapper.py
ned/candidate_generation/table_linker.py
ned/candidate_generation/table_linker_wrapper.py
ned/candidate_ranking/__init__.py
ned/candidate_ranking/columnwise_model.py
ned/candidate_ranking/contrastive_pairwise_model.py
ned/candidate_ranking/cr_dataset.py
ned/candidate_ranking/cr_method.py
ned/candidate_ranking/cr_searchscore.py
ned/candidate_ranking/cr_string_similarity.py
ned/candidate_ranking/cr_training.py
ned/candidate_ranking/dataset/__init__.py
ned/candidate_ranking/dataset/base.py
ned/candidate_ranking/dataset/basic_features.py
ned/candidate_ranking/dataset/matched_prop_feature.py
ned/candidate_ranking/dataset/types.py
ned/candidate_ranking/helpers/__init__.py
ned/candidate_ranking/helpers/dataset.py
ned/candidate_ranking/helpers/db_helper.py
ned/candidate_ranking/helpers/debug_helper.py
ned/candidate_ranking/helpers/training_helper.py
ned-1.11.1.dist-info/LICENSE
ned-1.11.1.dist-info/WHEEL
ned-1.11.1.dist-info/METADATA
ned-1.11.1.dist-info/RECORD
